.coveragerc
.travis.yml
CHANGELOG.rst
LICENSE
MANIFEST.in
README.md
VERSION
requirements-test.txt
requirements.txt
setup.cfg
setup.py
guillotina_pgfield/__init__.py
guillotina_pgfield/field.py
guillotina_pgfield/interfaces.py
guillotina_pgfield/utility.py
guillotina_pgfield.egg-info/PKG-INFO
guillotina_pgfield.egg-info/SOURCES.txt
guillotina_pgfield.egg-info/dependency_links.txt
guillotina_pgfield.egg-info/requires.txt
guillotina_pgfield.egg-info/top_level.txt
guillotina_pgfield.egg-info/zip-safe
guillotina_pgfield/tests/__init__.py
guillotina_pgfield/tests/conftest.py
guillotina_pgfield/tests/fixtures.py
guillotina_pgfield/tests/test_pgfield.py