Metadata-Version: 2.1
Name: guillotina-pgfield
Version: 1.0.1
Summary: Postgres field support for Guillotina
Home-page: https://flaps.io
License: BSD
Platform: UNKNOWN
Classifier: Development Status :: 4 - Beta
Classifier: Programming Language :: Python :: 3.7
Classifier: Topic :: Software Development :: Libraries :: Python Modules
